bidbot/BidBot.py
bidbot/BotClient.py
bidbot/GameState.py
bidbot/__init__.py
bidbot/varint.py
bidbot/protos/Comms_pb2.py
bidbot/protos/Comms_pb2.pyi
bidbot-0.1.4.dist-info/METADATA
bidbot-0.1.4.dist-info/WHEEL
bidbot-0.1.4.dist-info/licenses/LICENSE
bidbot-0.1.4.dist-info/RECORD
