Metadata-Version: 2.1
Name: bidbot
Version: 0.1.4
Summary: Client library for the bidding game.
Project-URL: Homepage, https://cybersmash.github.io
Project-URL: Bug Tracker, https://github.com/pypa/sampleproject/issues
Author-email: Jordan Sebastian <jordan.d.sebastian@gmail.com>
License-File: LICENSE
Classifier: License :: OSI Approved :: MIT License
Classifier: Operating System :: OS Independent
Classifier: Programming Language :: Python :: 3
Requires-Python: >=3.7
Requires-Dist: protobuf
Requires-Dist: rich
